[
  {
    "variation": "default",
    "name": "Default",
    "slice_type": "location_hero",
    "items": [],
    "primary": {
      "title": [
        {
          "type": "heading1",
          "text": "Transform granular e-services",
          "spans": []
        }
      ],
      "description": [
        {
          "type": "paragraph",
          "text": "Dolor deserunt minim aliquip do ut aute esse dolore nisi irure reprehenderit officia. Magna enim voluptate adipisicing aute sint ex anim adipisicing sit laborum aliqua deserunt mollit esse. Veniam sint do aute consequat laborum ad ullamco.",
          "spans": []
        }
      ],
      "hero": {
        "dimensions": {
          "width": 900,
          "height": 500
        },
        "alt": "Placeholder image",
        "copyright": null,
        "url": "https://images.unsplash.com/photo-1560457079-9a6532ccb118?w=900&h=500&fit=crop"
      },
      "link": {
        "link_type": "Web",
        "url": "http://twitter.com"
      },
      "button": [
        {
          "type": "paragraph",
          "text": "Nostrud voluptate dolor labore laboris excepteur exercitation sit voluptate mollit elit minim consectetur pariatur exercitation magna. Nostrud eu incididunt consequat non ea.",
          "spans": []
        }
      ]
    }
  }
]